{"data":{"site":{"siteMetadata":{"title":"Dmitriy An","author":"Dmitriy An"}},"markdownRemark":{"id":"98d54518-4aa4-5d78-9771-b688519969ff","excerpt":"Notesif project doesn’t have desktop / mobile image, you still have to put it in frontmatter and point it to ../no-image.png","html":"<h1>Notes</h1>\n<ul>\n<li>if project doesn’t have desktop / mobile image, you still have to put it in frontmatter and point it to ../no-image.png</li>\n</ul>","timeToRead":1,"frontmatter":{"title":"","date":null,"description":null}}},"pageContext":{"isCreatedByStatefulCreatePages":false,"slug":"/readme/","previous":{"fields":{"slug":"/learnings/"},"frontmatter":{"title":"On road learnings"}},"next":null}}